METHOD: getString()Ljava/lang/String;, FLAGS: 1, MAX STACK: 3, MAX LOCAL 4
 0 invokestatic org/wooddog/woodstub/core/WoodStub#isRunning()Z
 3 ifeq 69
 6 invokestatic org/wooddog/woodstub/core/WoodStub#pause()V
 9 invokestatic org/wooddog/woodstub/core/WoodStub#getStubFactory()Lorg/wooddog/woodstub/core/runtime/StubFactory;
12 aload_0
13 ldc org/wooddog/woodstub/core/stubgenerator/templates/GetString#getString()Ljava/lang/String;
15 invokeinterface org/wooddog/woodstub/core/runtime/StubFactory#createStub(Ljava/lang/Object;Ljava/lang/String;)Lorg/wooddog/woodstub/core/runtime/Stub; 3 0
20 astore_1
21 aload_1
22 ifnull 38
25 aload_1
26 iconst_0
27 anewarray java/lang/String
30 iconst_0
31 anewarray java/lang/Object
34 invokeinterface org/wooddog/woodstub/core/runtime/Stub#setParameters([Ljava/lang/String;[Ljava/lang/Object;)V 3 0
39 aload_1
40 invokeinterface org/wooddog/woodstub/core/runtime/Stub#execute()V 1 0
45 aload_1
46 invokeinterface org/wooddog/woodstub/core/runtime/Stub#getResult()Ljava/lang/Object; 1 0
51 checkcast java/lang/String
54 astore_2
55 invokestatic org/wooddog/woodstub/core/WoodStub#resume()V
58 aload_2
59 areturn
60 invokestatic org/wooddog/woodstub/core/WoodStub#resume()V
63 goto 9
66 astore_3
67 invokestatic org/wooddog/woodstub/core/WoodStub#resume()V
70 aload_3
71 athrow
72 aconst_null
73 areturn
